{"NodeType":"File","Doc":null,"Package":null,"Name":{"NodeType":"Ident","Name":"main"},"Decls":[{"NodeType":"FuncDecl","Recv":null,"Name":{"NodeType":"Ident","Name":"plus"},"Type":{"NodeType":"FuncType","TypeParams":null,"Params":{"NodeType":"FieldList","List":[{"NodeType":"Field","Names":[{"NodeType":"Ident","Name":"a"}],"Type":{"NodeType":"Ident","Name":"int"}},{"NodeType":"Field","Names":[{"NodeType":"Ident","Name":"b"}],"Type":{"NodeType":"Ident","Name":"int"}}]},"Results":{"NodeType":"FieldList","List":[{"NodeType":"Field","Names":null,"Type":{"NodeType":"Ident","Name":"int"}}]}},"Body":{"NodeType":"BlockStmt","List":[{"NodeType":"AssignStmt","Lhs":[{"NodeType":"Ident","Name":"a"}],"Tok":"=","Rhs":[{"NodeType":"BinaryExpr","X":{"NodeType":"Ident","Name":"b"},"Op":"+","Y":{"NodeType":"Ident","Name":"z"}}]},{"NodeType":"AssignStmt","Lhs":[{"NodeType":"Ident","Name":"b"}],"Tok":"=","Rhs":[{"NodeType":"BinaryExpr","X":{"NodeType":"Ident","Name":"b"},"Op":"+","Y":{"NodeType":"BasicLit","Kind":"INT","Value":"2"}}]},{"NodeType":"ReturnStmt","Results":[{"NodeType":"BinaryExpr","X":{"NodeType":"Ident","Name":"a"},"Op":"+","Y":{"NodeType":"Ident","Name":"b"}}]}]}},{"NodeType":"FuncDecl","Recv":null,"Name":{"NodeType":"Ident","Name":"main"},"Type":{"NodeType":"FuncType","TypeParams":null,"Params":{"NodeType":"FieldList","List":null},"Results":null},"Body":{"NodeType":"BlockStmt","List":[{"NodeType":"DeclStmt","Decl":{"NodeType":"GenDecl","Tok":"var","Specs":[{"NodeType":"ValueSpec","Names":[{"NodeType":"Ident","Name":"a"}],"Type":null,"Values":[{"NodeType":"BasicLit","Kind":"INT","Value":"2"}]}]}},{"NodeType":"DeclStmt","Decl":{"NodeType":"GenDecl","Tok":"var","Specs":[{"NodeType":"ValueSpec","Names":[{"NodeType":"Ident","Name":"res"}],"Type":null,"Values":[{"NodeType":"CallExpr","Fun":{"NodeType":"Ident","Name":"plus"},"Args":[{"NodeType":"BasicLit","Kind":"INT","Value":"1"},{"NodeType":"BasicLit","Kind":"INT","Value":"2"}]}]}]}}]}}],"Imports":null,"Unresolved":null,"Comments":null,"FileSet":{"Base":151,"Files":[{"Name":"code.go","Base":1,"Size":149,"Lines":[0,13,14,44,58,72,89,91,92,106,107,121,146,147],"Infos":null}]}}
